aio_yandex_translate/__init__.py
aio_yandex_translate/translator.py
aio_yandex_translate-1.1.1.dist-info/LICENSE
aio_yandex_translate-1.1.1.dist-info/METADATA
aio_yandex_translate-1.1.1.dist-info/WHEEL
aio_yandex_translate-1.1.1.dist-info/top_level.txt
aio_yandex_translate-1.1.1.dist-info/RECORD
