Metadata-Version: 2.1
Name: aio-yandex-translate
Version: 1.1.1
Summary: Yandex translate async api wrapper
Home-page: https://github.com/Rud356/aioyatr
Author: Rud356
Author-email: devastator12a@mail.ru
License: GPLv3
Platform: UNKNOWN
Classifier: Programming Language :: Python :: 3.6
Classifier: Programming Language :: Python :: 3.7
Classifier: Programming Language :: Python :: 3.8
Classifier: License :: OSI Approved :: GNU General Public License v3 or later (GPLv3+)
Classifier: Operating System :: OS Independent
Classifier: Intended Audience :: Developers
Classifier: Natural Language :: English
Requires-Python: >=3.6
Requires-Dist: aiohttp (>=3.6)
Requires-Dist: aiohttp-proxy (>=0.1.2)
Provides-Extra: ujson
